MANIFEST.in
README.rst
setup.py
django_favman.egg-info/PKG-INFO
django_favman.egg-info/SOURCES.txt
django_favman.egg-info/dependency_links.txt
django_favman.egg-info/not-zip-safe
django_favman.egg-info/top_level.txt
favman/__init__.py
favman/admin.py
favman/forms.py
favman/models.py
favman/tests.py
favman/urls.py
favman/views.py
favman/locale/fr/LC_MESSAGES/django.mo
favman/locale/fr/LC_MESSAGES/django.po
favman/migrations/0001_initial.py
favman/migrations/__init__.py
favman/static/css/favorites.css
favman/static/img/fav-hover.png
favman/static/img/fav-in-hover.png
favman/static/img/fav-in.png
favman/static/img/fav-out.png
favman/static/js/favorites.js
favman/templates/favman/_item.html
favman/templates/favman/_media.html
favman/templates/favman/base.html
favman/templates/favman/favorites_list.html
favman/templates/favman/user_messages/_user_not_logged.html
favman/templatetags/__init__.py
favman/templatetags/favman_tags.py