Metadata-Version: 1.1
Name: django-favman
Version: 0.1.2
Summary: Let users bookmark their favorite objects
Home-page: UNKNOWN
Author: Luc Jean
Author-email: ljean@apidev.fr
License: GNU LGPL
Platform: UNKNOWN
Classifier: Development Status :: 3 - Alpha
Classifier: Framework :: Django
Classifier: Environment :: Web Environment
Classifier: Intended Audience :: Developers
Classifier: License :: OSI Approved :: GNU Lesser General Public License v3 or later (LGPLv3+)
Classifier: Programming Language :: Python
Classifier: Operating System :: OS Independent
Classifier: Topic :: Software Development :: Libraries
